twitter_openapi_python/__init__.py
twitter_openapi_python/client.py
twitter_openapi_python/py.typed
twitter_openapi_python/tid.py
twitter_openapi_python/api/__init__.py
twitter_openapi_python/api/default_api.py
twitter_openapi_python/api/initial_state_api.py
twitter_openapi_python/api/post_api.py
twitter_openapi_python/api/tweet_api.py
twitter_openapi_python/api/user_api.py
twitter_openapi_python/api/user_list_api.py
twitter_openapi_python/api/users_api.py
twitter_openapi_python/api/v11_get_api.py
twitter_openapi_python/api/v11_post_api.py
twitter_openapi_python/models/__init__.py
twitter_openapi_python/models/base.py
twitter_openapi_python/models/header.py
twitter_openapi_python/models/initial_state.py
twitter_openapi_python/models/response.py
twitter_openapi_python/models/timeline.py
twitter_openapi_python/utils/__init__.py
twitter_openapi_python/utils/api.py
twitter_openapi_python-0.0.42.dist-info/licenses/LICENSE
twitter_openapi_python-0.0.42.dist-info/licenses/LICENSE.AGPL
twitter_openapi_python-0.0.42.dist-info/METADATA
twitter_openapi_python-0.0.42.dist-info/WHEEL
twitter_openapi_python-0.0.42.dist-info/top_level.txt
twitter_openapi_python-0.0.42.dist-info/RECORD
