Metadata-Version: 2.4
Name: twitter_openapi_python
Version: 0.0.42
Summary: Twitter OpenAPI
Home-page: https://github.com/fa0311/twitter_openapi_python
Author: fa0311
Author-email: yuki@yuki0311.com
License: proprietary or AGPL-3.0-or-later
Keywords: OpenAPI,OpenAPI-Generator,Twitter OpenAPI
License-File: LICENSE
License-File: LICENSE.AGPL
Requires-Dist: twitter_openapi_python_generated==0.0.33
Requires-Dist: pydantic>=2.6
Requires-Dist: urllib3<3.0.0,>=2.1.0
Requires-Dist: xclienttransaction<2.0.0,>=1.0.0
Dynamic: author
Dynamic: author-email
Dynamic: description
Dynamic: description-content-type
Dynamic: home-page
Dynamic: keywords
Dynamic: license
Dynamic: license-file
Dynamic: requires-dist
Dynamic: summary
